retnet/__init__.py
retnet-0.0.1.dev0.dist-info/METADATA
retnet-0.0.1.dev0.dist-info/WHEEL
retnet-0.0.1.dev0.dist-info/top_level.txt
retnet-0.0.1.dev0.dist-info/RECORD
